progresslogger.py
progresslogger-1.1.0.dist-info/LICENSE
progresslogger-1.1.0.dist-info/METADATA
progresslogger-1.1.0.dist-info/WHEEL
progresslogger-1.1.0.dist-info/top_level.txt
progresslogger-1.1.0.dist-info/RECORD
