Metadata-Version: 2.1
Name: progresslogger
Version: 1.1.0
Summary: A simple, lightweight logger for your Python loops
Home-page: https://github.com/michael-genson/progresslogger
Author: Michael Genson
Author-email: genson.michael@gmail.com
License: GNU
Platform: UNKNOWN
